package_sh/__init__.py
package_sh/random_f.py
package_sh_pkg-0.0.1.dist-info/METADATA
package_sh_pkg-0.0.1.dist-info/WHEEL
package_sh_pkg-0.0.1.dist-info/top_level.txt
package_sh_pkg-0.0.1.dist-info/RECORD
